lutron_integration_tools/__init__.py
lutron_integration_tools/monitor.py
lutron_integration_tools/py.typed
lutron_integration_tools-0.0.0a1.dist-info/WHEEL
lutron_integration_tools-0.0.0a1.dist-info/entry_points.txt
lutron_integration_tools-0.0.0a1.dist-info/METADATA
lutron_integration_tools-0.0.0a1.dist-info/RECORD
