Metadata-Version: 2.3
Name: lutron-integration-tools
Version: 0.0.0a1
Summary: Command-line tools for lutron-integration
Keywords: QSE-CI-NWK-E,Lutron,QS Standalone,Grafik Eye
Classifier: Development Status :: 3 - Alpha
Classifier: Intended Audience :: End Users/Desktop
Classifier: Programming Language :: Python :: 3
Requires-Dist: lutron-integration==0.0.0a1
Requires-Python: >=3.12
